workhours/__init__.py
login_workhours-0.1.dist-info/METADATA
login_workhours-0.1.dist-info/WHEEL
login_workhours-0.1.dist-info/entry_points.txt
login_workhours-0.1.dist-info/top_level.txt
login_workhours-0.1.dist-info/RECORD
