Metadata-Version: 2.1
Name: login-workhours
Version: 0.1
Summary: Compute working hours based on login / logouts events.
Home-page: https://framagit.org/almet/workhours
Author: Alexis Métaireau & contributors
Author-email: alexis@notmyidea.org
License: Custom BSD Beerware
Keywords: time-management
Platform: UNKNOWN
Classifier: Programming Language :: Python :: 3.7
Requires-Dist: utmp
Requires-Dist: tabulate
